{
    "Timestamp": "1/2/2020 19:59:05",
    "Title": "Pteromys: Interactive Design and Optimization of Free-formed Free-flight Model Airplanes",
    "DOI": "10.1145/2601097.2601129",
    "PDF availability (beside dl.acm)": "On the author(s) website or its institution",
    "Is the code or software publicly available ?": "No",
    "Availability": "",
    "Main languages": "",
    "How long did take for you to evaluate the code this paper (if any)?": 1,
    "Build info / instructions": "",
    "arXiv (page URL)": "",
    "code URL": "",
    "code URL  2": "",
    "PDF URL": "http://www.nobuyuki-umetani.com/publication/2014_sigg_pteromys/2014_siggraph_GliderDesign.pdf",
    "License type": "",
    "Build mechanism": "",
    "Mandatory Software dependencies": "",
    "Feedback [easy deps]": "",
    "Feedbacks [easy to find/install dependencies  (5=easy)]": "",
    "Feedbacks [easy to configure/build (5=easy)]": "",
    "Feedbacks [easy to fix bugs (5=easy N/A if no bug)]": "",
    "Execution experience [Row 1]": "",
    "Does the code need data (other than examples/inputs) ?": "",
    "Available data (provided or url / ref)": "",
    "License for the data (if any)": "",
    "Feedbacks [easy to adapt / use in other contexts (5=easy)]": "",
    "Feedbacks [Interface user-friendly (5=easy)]": "",
    "Documentation": "",
    "Authors": "Academia, Private Companies",
    "ACM 1": "Geometric topology",
    "ACM 2": "Physical simulation",
    "ACM 3": "Shape modeling",
    "Feedbacks [if matlab does it run on OSS alternatives (5=easy)]": "",
    "OS of the test": "",
    "General comments": "",
    "Does the paper already have a reproducibility stamp": "No",
    "Citation count (google scholar)": 85,
    "List of the required dependencies (if any, \"/\" separated, ex: matlab, libpng,cgal...)": "",
    "Project URL": "http://www.nobuyuki-umetani.com/publication/2014_sigg_pteromys/2014_siggraph_GliderDesign.html",
    "Did I manage to perform a complete test (deps/build)?": "",
    "Year": 2014,
    "Misc. comment": "",
    "Software Type": "",
    "Topic": "Fabrication",
    "Deep learning": "False",
    "hasThumbnail": true,
    "Open access": false,
    "Feedbacks [could reproduce results (5=highly confident)]": "",
    "Could paper be trivially implemented using the pseudo-code": "",
    "Reviewer": 4,
    "Documentation score": 0,
    "Paper authors": [
        {
            "given": "Nobuyuki",
            "family": "Umetani",
            "sequence": "first",
            "affiliation": []
        },
        {
            "given": "Yuki",
            "family": "Koyama",
            "sequence": "additional",
            "affiliation": []
        },
        {
            "given": "Ryan",
            "family": "Schmidt",
            "sequence": "additional",
            "affiliation": []
        },
        {
            "given": "Takeo",
            "family": "Igarashi",
            "sequence": "additional",
            "affiliation": []
        }
    ],
    "Altmetric score": 10,
    "Altmetric badge": "https://badges.altmetric.com/?size=64&score=10&types=mmmmmmmm",
    "Altmetric url": "http://www.altmetric.com/details.php?citation_id=2579692"
}